{
  "name": "Soul Bind Plane",
  "summary": "Anchors soul flux as a planar spread at self reach, targeting a filtered selection with short timed hold with active regulation while it runs.",
  "effect_description": "Anchors soul flux as a planar spread at self reach, targeting a filtered selection with short timed hold with active regulation while it runs. A circle bind/control recipe that channels soul discipline into soul output. It applies a plane pattern against filter across self reach with timed short persistence.",
  "hook": "Bind",
  "mode": "Control",
  "shape": "Circle",
  "discipline": "Soul",
  "output_mode": "Soul",
  "pattern": "Plane",
  "reach": "Self",
  "persistence": "Timed Short",
  "target_spec": "Filter",
  "sustained_minutes": 0,
  "hook_mode_multiplier": 2.16,
  "hook_mode_flat_w": 0,
  "notes": "Generated automatically from randomized sigil variables."
}