{
  "name": "Soul Emit Point",
  "summary": "Releases soul kinetic flux as a point focus at self reach, targeting a prepared surface with immediate discharge by creating a fresh flux expression.",
  "effect_description": "Releases soul kinetic flux as a point focus at self reach, targeting a prepared surface with immediate discharge by creating a fresh flux expression. A pentagon emit/create recipe that channels soul discipline into kinetic output. It applies a point pattern against surface across self reach with immediate persistence.",
  "hook": "Emit",
  "mode": "Create",
  "shape": "Pentagon",
  "discipline": "Soul",
  "output_mode": "Kinetic",
  "pattern": "Point",
  "reach": "Self",
  "persistence": "Immediate",
  "target_spec": "Surface",
  "sustained_minutes": 0,
  "hook_mode_multiplier": 1.15,
  "hook_mode_flat_w": 0,
  "notes": "Generated automatically from randomized sigil variables."
}