{
  "name": "Binding Dampen Point",
  "summary": "Reduces binding reactive flux as a point focus at anchored reach, targeting a marked signature with long timed hold by changing existing conditions.",
  "effect_description": "Reduces binding reactive flux as a point focus at anchored reach, targeting a marked signature with long timed hold by changing existing conditions. A circle dampen/affect recipe that channels binding discipline into reactive output. It applies a point pattern against marked across anchored reach with timed long persistence.",
  "hook": "Dampen",
  "mode": "Affect",
  "shape": "Circle",
  "discipline": "Binding",
  "output_mode": "Reactive",
  "pattern": "Point",
  "reach": "Anchored",
  "persistence": "Timed Long",
  "target_spec": "Marked",
  "sustained_minutes": 0,
  "hook_mode_multiplier": 1.9,
  "hook_mode_flat_w": 0,
  "notes": "Generated automatically from randomized sigil variables."
}